LICENSE.md
README.md
setup.py
pnytter/__init__.py
pnytter/exceptions.py
pnytter/pnytter.py
pnytter/utils.py
pnytter.egg-info/PKG-INFO
pnytter.egg-info/SOURCES.txt
pnytter.egg-info/dependency_links.txt
pnytter.egg-info/requires.txt
pnytter.egg-info/top_level.txt
pnytter/models/__init__.py
pnytter/models/base.py
pnytter/models/generic.py
pnytter/models/profiles.py
pnytter/models/tweets.py
pnytter/nitter_parser/__init__.py
pnytter/nitter_parser/base.py
pnytter/nitter_parser/profiles.py
pnytter/nitter_parser/tweets.py
tests/__init__.py
tests/_test_pnytter_tweets_data.py
tests/conftest.py
tests/test_pnytter_api.py
tests/test_pnytter_profiles.py
tests/test_pnytter_tweets.py